ConfigurerControl/__init__.py
ConfigurerControl/actions.py
ConfigurerControl/parameters.py
configurercontrol-0.5.10.dist-info/METADATA
configurercontrol-0.5.10.dist-info/WHEEL
configurercontrol-0.5.10.dist-info/top_level.txt
configurercontrol-0.5.10.dist-info/RECORD
