Metadata-Version: 2.4
Name: ConfigurerControl
Version: 0.5.10
Summary: dlms-spodes
Author-email: Sergei Vasilev <vasilsv@ite-ng.ru>
Project-URL: Source, http://git.ite-ng.ru/dep/configurer_control_services_prj
Keywords: dlms,GUI,MVC
Classifier: Programming Language :: Python :: 3
Classifier: License :: OSI Approved :: MIT License
Classifier: Operating System :: OS Independent
Requires-Python: >=3.12
Requires-Dist: Pillow>=10.4.0
Requires-Dist: DLMS-SPODES<0.87,>=0.85.1
Requires-Dist: DLMS_SPODES_client<0.18,>=0.16.3
Requires-Dist: DLMSCommunicationProfile<0.2,>=0.1.4
Requires-Dist: tKot>=0.7.9
